{
    "indexes": [
        {
            "collectionGroup": "taxData",
            "queryScope": "COLLECTION",
            "fields": [
                {
                    "fieldPath": "userId",
                    "order": "ASCENDING"
                },
                {
                    "fieldPath": "year",
                    "order": "DESCENDING"
                },
                {
                    "fieldPath": "createdAt",
                    "order": "DESCENDING"
                }
            ]
        },
        {
            "collectionGroup": "transactions",
            "queryScope": "COLLECTION",
            "fields": [
                {
                    "fieldPath": "userId",
                    "order": "ASCENDING"
                },
                {
                    "fieldPath": "createdAt",
                    "order": "DESCENDING"
                }
            ]
        },
        {
            "collectionGroup": "messages",
            "queryScope": "COLLECTION",
            "fields": [
                {
                    "fieldPath": "vertexChatRoomId",
                    "order": "ASCENDING"
                },
                {
                    "fieldPath": "createdAt",
                    "order": "ASCENDING"
                }
            ]
        },
        {
            "collectionGroup": "chatRooms",
            "queryScope": "COLLECTION",
            "fields": [
                {
                    "fieldPath": "userId",
                    "order": "ASCENDING"
                },
                {
                    "fieldPath": "createdAt",
                    "order": "DESCENDING"
                }
            ]
        }
    ],
    "fieldOverrides": []
}